cdk_deployer/__init__.py
cdk_deployer/py.typed
cdk_deployer/_jsii/__init__.py
cdk_deployer/_jsii/cdk-deployer@1.0.13.jsii.tgz
cdk_deployer-1.0.13.dist-info/LICENSE
cdk_deployer-1.0.13.dist-info/METADATA
cdk_deployer-1.0.13.dist-info/NOTICE
cdk_deployer-1.0.13.dist-info/WHEEL
cdk_deployer-1.0.13.dist-info/top_level.txt
cdk_deployer-1.0.13.dist-info/RECORD
