Metadata-Version: 2.1
Name: cdk-deployer
Version: 1.0.13
Summary: A construct library for deploying artifacts via CodeDeploy inside of a AWS CDK application.
Home-page: https://github.com/cdklabs/cdk-deployer
Author: Jeff Gardner
License: Apache-2.0
Project-URL: Source, https://github.com/cdklabs/cdk-deployer
Platform: UNKNOWN
Classifier: Intended Audience :: Developers
Classifier: Operating System :: OS Independent
Classifier: Programming Language :: JavaScript
Classifier: Programming Language :: Python :: 3 :: Only
Classifier: Programming Language :: Python :: 3.7
Classifier: Programming Language :: Python :: 3.8
Classifier: Programming Language :: Python :: 3.9
Classifier: Programming Language :: Python :: 3.10
Classifier: Typing :: Typed
Classifier: Development Status :: 5 - Production/Stable
Classifier: License :: OSI Approved
Requires-Python: ~=3.7
License-File: LICENSE
License-File: NOTICE
Requires-Dist: aws-cdk.aws-autoscaling (<2.0.0,>=1.173.0)
Requires-Dist: aws-cdk.aws-codedeploy (<2.0.0,>=1.173.0)
Requires-Dist: aws-cdk.aws-ec2 (<2.0.0,>=1.173.0)
Requires-Dist: aws-cdk.aws-iam (<2.0.0,>=1.173.0)
Requires-Dist: aws-cdk.aws-lambda (<2.0.0,>=1.173.0)
Requires-Dist: aws-cdk.aws-s3-assets (<2.0.0,>=1.173.0)
Requires-Dist: aws-cdk.aws-s3 (<2.0.0,>=1.173.0)
Requires-Dist: aws-cdk.core (<2.0.0,>=1.173.0)
Requires-Dist: aws-cdk.custom-resources (<2.0.0,>=1.173.0)
Requires-Dist: constructs (<4.0.0,>=3.2.27)
Requires-Dist: jsii (<2.0.0,>=1.67.0)
Requires-Dist: publication (>=0.0.3)
Requires-Dist: typeguard (~=2.13.3)
